{
  "formatos": {
    "redondo": {
      "F_Z": [0.78, 0.92],
      "Z_M": [0.85, 1.00],
      "F_M": [0.78, 0.92],
      "Z_H": [0.48, 0.60],
      "H_Z": [1.60, 2.10],
      "H_F": [1.40, 1.80],
      "H_M": [1.45, 1.85],
      "T1_T3": [0.90, 1.10],
      "T2_T3": [0.85, 1.00],
      "T1_T2": [0.90, 1.10],
      "A_mand": [60, 2000],
      "A_zig": [60, 2000],
      "F_H_total": [0.30, 0.38],
      "Z_H_total": [0.35, 0.43],
      "M_H_total": [0.30, 0.38],
      "golden_ratio_face": [1.45, 1.70],
      "WHR": [0.45, 0.63],
      "comprimento_rel": [0.95, 1.25]
    },

    "oval": {
      "F_Z": [0.72, 0.86],
      "Z_M": [0.70, 0.82],
      "F_M": [0.62, 0.76],
      "Z_H": [0.38, 0.48],
      "H_Z": [2.00, 2.60],
      "H_F": [1.80, 2.30],
      "H_M": [1.85, 2.30],
      "T1_T3": [0.75, 0.90],
      "T2_T3": [0.75, 0.88],
      "T1_T2": [0.77, 0.90],
      "A_mand": [60, 2000],
      "A_zig": [60, 2000],
      "F_H_total": [0.26, 0.32],
      "Z_H_total": [0.32, 0.38],
      "M_H_total": [0.28, 0.34],
      "golden_ratio_face": [1.55, 1.90],
      "WHR": [0.36, 0.50],
      "comprimento_rel": [1.30, 1.60]
    },

    "quadrado": {
      "F_Z": [0.78, 0.92],
      "Z_M": [0.82, 0.95],
      "F_M": [0.78, 0.92],
      "Z_H": [0.45, 0.55],
      "H_Z": [1.80, 2.25],
      "H_F": [1.55, 2.00],
      "H_M": [1.60, 2.05],
      "T1_T3": [0.95, 1.20],
      "T2_T3": [0.90, 1.10],
      "T1_T2": [0.95, 1.20],
      "A_mand": [60, 2000],
      "A_zig": [60, 2000],
      "F_H_total": [0.30, 0.38],
      "Z_H_total": [0.35, 0.45],
      "M_H_total": [0.32, 0.42],
      "golden_ratio_face": [1.45, 1.85],
      "WHR": [0.48, 0.62],
      "comprimento_rel": [1.20, 1.50]
    },

    "retangular": {
      "F_Z": [0.70, 0.82],
      "Z_M": [0.62, 0.75],
      "F_M": [0.62, 0.75],
      "Z_H": [0.32, 0.42],
      "H_Z": [2.40, 3.20],
      "H_F": [2.30, 3.00],
      "H_M": [2.30, 3.00],
      "T1_T3": [0.65, 0.78],
      "T2_T3": [0.60, 0.75],
      "T1_T2": [0.70, 0.85],
      "A_mand": [60, 2000],
      "A_zig": [60, 2000],
      "F_H_total": [0.20, 0.28],
      "Z_H_total": [0.25, 0.33],
      "M_H_total": [0.22, 0.32],
      "golden_ratio_face": [1.60, 2.10],
      "WHR": [0.28, 0.40],
      "comprimento_rel": [1.60, 2.00]
    },

    "triangular": {
      "F_Z": [0.60, 0.72],
      "Z_M": [0.75, 0.90],
      "F_M": [0.85, 1.00],
      "Z_H": [0.40, 0.52],
      "H_Z": [1.90, 2.40],
      "H_F": [1.40, 1.90],
      "H_M": [1.40, 1.90],
      "T1_T3": [0.80, 1.10],
      "T2_T3": [0.85, 1.05],
      "T1_T2": [0.70, 0.85],
      "A_mand": [60, 2000],
      "A_zig": [60, 2000],
      "F_H_total": [0.28, 0.36],
      "Z_H_total": [0.33, 0.45],
      "M_H_total": [0.35, 0.48],
      "golden_ratio_face": [1.40, 1.80],
      "WHR": [0.38, 0.48],
      "comprimento_rel": [1.30, 1.60]
    },

    "losango": {
      "F_Z": [0.68, 0.80],
      "Z_M": [0.85, 1.00],
      "F_M": [0.60, 0.75],
      "Z_H": [0.42, 0.55],
      "H_Z": [1.80, 2.30],
      "H_F": [1.55, 2.10],
      "H_M": [1.70, 2.20],
      "T1_T3": [0.80, 1.05],
      "T2_T3": [0.90, 1.10],
      "T1_T2": [0.75, 0.90],
      "A_mand": [60, 2000],
      "A_zig": [60, 2000],
      "F_H_total": [0.26, 0.34],
      "Z_H_total": [0.34, 0.42],
      "M_H_total": [0.26, 0.36],
      "golden_ratio_face": [1.50, 1.90],
      "WHR": [0.40, 0.55],
      "comprimento_rel": [1.35, 1.60]
    },

    "coracao": {
      "F_Z": [0.82, 0.94],
      "Z_M": [0.75, 0.88],
      "F_M": [0.55, 0.70],
      "Z_H": [0.40, 0.52],
      "H_Z": [1.90, 2.40],
      "H_F": [1.30, 1.70],
      "H_M": [1.50, 1.90],
      "T1_T3": [0.60, 0.80],
      "T2_T3": [0.70, 0.90],
      "T1_T2": [0.82, 1.00],
      "A_mand": [60, 2000],
      "A_zig": [60, 2000],
      "F_H_total": [0.28, 0.36],
      "Z_H_total": [0.32, 0.40],
      "M_H_total": [0.25, 0.34],
      "golden_ratio_face": [1.40, 1.80],
      "WHR": [0.38, 0.48],
      "comprimento_rel": [1.25, 1.55]
    }
  }
}
